ValeraOlmosPote/__init__.py
ValeraOlmosPote/statistics.py
valeraolmospote-1.5.0.dist-info/METADATA
valeraolmospote-1.5.0.dist-info/WHEEL
valeraolmospote-1.5.0.dist-info/licenses/LICENSE
valeraolmospote-1.5.0.dist-info/RECORD
