Metadata-Version: 2.1
Name: ValeraOlmosPote
Version: 1.5.0
Summary: Segundo Proyecto del curso Machine Learning Para Economistas
Project-URL: Homepage, https://github.com/pypa/sampleproject
Project-URL: Bug Tracker, https://github.com/pypa/sampleproject/issues
Author-email: "Luis Valera, Sara Olmos y Karol Pote" <luchovalrodr@outlook.com>
License-File: LICENSE
Classifier: License :: OSI Approved :: MIT License
Classifier: Operating System :: OS Independent
Classifier: Programming Language :: Python :: 3
Requires-Python: >=3.7
